gpep517/__init__.py
gpep517/__main__.py
gpep517/build.py
gpep517/install.py
gpep517/qa.py
gpep517/utils.py
gpep517-19.dist-info/entry_points.txt
gpep517-19.dist-info/licenses/COPYING
gpep517-19.dist-info/WHEEL
gpep517-19.dist-info/METADATA
gpep517-19.dist-info/RECORD
