Metadata-Version: 2.4
Name: gpep517
Version: 19
Summary: Python package builder and installer for non-pip-centric world
Author-email: Michał Górny <mgorny@gentoo.org>
Requires-Python: >=3.8
Classifier: Development Status :: 5 - Production/Stable
Classifier: Environment :: Console
Classifier: Intended Audience :: Developers
Classifier: Intended Audience :: System Administrators
Classifier: License :: OSI Approved :: GNU General Public License v2 or later (GPLv2+)
Classifier: Programming Language :: Python :: 3 :: Only
Classifier: Topic :: System :: Installation/Setup
Classifier: Topic :: System :: Software Distribution
License-File: COPYING
Requires-Dist: installer >= 0.5
Requires-Dist: tomli >= 1.2.3; python_version < '3.11'
Requires-Dist: pytest ; extra == "test"
Requires-Dist: flit_core ; extra == "test-full"
Requires-Dist: hatchling ; extra == "test-full"
Requires-Dist: pdm-pep517 ; extra == "test-full"
Requires-Dist: poetry-core ; extra == "test-full"
Requires-Dist: setuptools ; extra == "test-full"
Requires-Dist: wheel ; extra == "test-full"
Project-URL: Home, https://github.com/mgorny/gpep517/
Provides-Extra: test
Provides-Extra: test-full
